digitgen/__init__.py
digitgen/digit_generator.py
digitgen/augmentation/__init__.py
digitgen/augmentation/augmentation.py
digitgen/augmentation/noise.py
digitgen/augmentation/shearing.py
digitgen/digit/__init__.py
digitgen/digit/digits.py
digitgen/font/__init__.py
digitgen/font/font_config.py
digitgen/font/fonts/terminal-grotesque-regular.ttf
digitgen/utils/__init__.py
digitgen/utils/config.py
digitgen/utils/helper.py
digitgen-0.6.9.dist-info/LICENCE
digitgen-0.6.9.dist-info/METADATA
digitgen-0.6.9.dist-info/WHEEL
digitgen-0.6.9.dist-info/top_level.txt
digitgen-0.6.9.dist-info/RECORD
